fit2gpx_lightning-0.1.2.dist-info/METADATA
fit2gpx_lightning-0.1.2.dist-info/WHEEL
fit2gpx_lightning/__init__.py
fit2gpx_lightning/fit2gpx_lightning.pypy39-pp73-aarch64-linux-gnu.so
fit2gpx_lightning-0.1.2.dist-info/RECORD
