Metadata-Version: 2.4
Name: fit2gpx-lightning
Version: 0.1.2
Classifier: Programming Language :: Rust
Classifier: Programming Language :: Python :: 3
Classifier: Programming Language :: Python :: 3.8
Classifier: Programming Language :: Python :: 3.9
Classifier: Programming Language :: Python :: 3.10
Classifier: Programming Language :: Python :: 3.11
Classifier: Programming Language :: Python :: 3.12
Classifier: Programming Language :: Python :: 3.13
Summary: Fast FIT to GPX converter - replacement for fit2gpx
Keywords: fit,gpx,garmin,strava,conversion
License: MIT
Requires-Python: >=3.8
